{"legislative_session": "2025_26", "identifier": "HB 1088", "title": "Chiropractors; replace term chiropractor with chiropractic physician", "from_organization": "~{\"classification\": \"lower\"}", "classification": ["bill"], "subject": [], "abstracts": [{"note": "description", "abstract": "A BILL to be entitled an Act to amend Chapter 9 of Title 43 of the Official Code of Georgia Annotated, relating to chiropractors, so as to replace the term \"chiropractor\" with \"chiropractic physician\"; to amend Title 14 of the Official Code of Georgia Annotated, relating to corporations, partnerships, and associations, so as to provide for professional corporations jointly owned by chiropractic physicians and physicians; to amend Title 45 of the Official Code of Georgia Annotated, relating to public officers and employees, so as to provide for conforming changes in terminology; to amend various titles of the Official Code of Georgia Annotated, so as to provide for conforming changes in terminology; to provide for related matters; to provide for an effective date; to repeal conflicting laws; and for other purposes."}], "other_titles": [], "other_identifiers": [], "actions": [{"description": "House Hopper", "date": "2026-01-29", "organization_id": "~{\"classification\": \"lower\"}", "classification": ["introduction"], "related_entities": []}, {"description": "House First Readers", "date": "2026-02-02", "organization_id": "~{\"classification\": \"lower\"}", "classification": ["reading-1"], "related_entities": []}, {"description": "House Second Readers", "date": "2026-02-03", "organization_id": "~{\"classification\": \"lower\"}", "classification": ["reading-2"], "related_entities": []}], "sponsorships": [{"name": "Karen Mathiak", "classification": "primary", "entity_type": "person", "primary": true, "person_id": "~{\"name\": \"Karen Mathiak\"}", "organization_id": null}, {"name": "Matt Reeves", "classification": "primary", "entity_type": "person", "primary": true, "person_id": "~{\"name\": \"Matt Reeves\"}", "organization_id": null}, {"name": "Anissa Jones", "classification": "primary", "entity_type": "person", "primary": true, "person_id": "~{\"name\": \"Anissa Jones\"}", "organization_id": null}, {"name": "Gerald Greene", "classification": "primary", "entity_type": "person", "primary": true, "person_id": "~{\"name\": \"Gerald Greene\"}", "organization_id": null}, {"name": "Stacey Evans", "classification": "primary", "entity_type": "person", "primary": true, "person_id": "~{\"name\": \"Stacey Evans\"}", "organization_id": null}], "related_bills": [], "versions": [{"note": "LC 52 0963/a", "links": [{"url": "http://www.legis.ga.gov/Legislation/20252026/240835.pdf", "media_type": "application/pdf"}], "date": "", "classification": "", "extras": {"_internal_document_id": 240835, "_version_id": 2}}], "documents": [], "citations": [], "sources": [{"url": "http://webservices.legis.ga.gov/GGAServices/Members/Service.svc?wsdl", "note": "api"}, {"url": "http://webservices.legis.ga.gov/GGAServices/Legislation/Service.svc?wsdl", "note": "api"}, {"url": "https://www.legis.ga.gov/legislation/72594", "note": ""}], "extras": {"guid": 72594}, "jurisdiction": {"id": "ocd-jurisdiction/country:us/state:ga/government", "name": "Georgia", "classification": "state", "division_id": "ocd-division/country:us/state:ga"}, "scraped_at": "2026-02-17T09:48:13+00:00", "_id": "c6e71440-0be5-11f1-b8a4-5a60490bb6ca"}