{"legislative_session": "2025_26", "identifier": "HB 1450", "title": "State militia; oversight of any deployment of the National Guard by the Governor; provide", "from_organization": "~{\"classification\": \"lower\"}", "classification": ["bill"], "subject": ["MILITARY, EMERGENCY MANAGEMENT, AND VETERANS AFFAIRS", "PUBLIC OFFICERS AND EMPLOYEES"], "abstracts": [{"note": "description", "abstract": "A BILL to be entitled an Act to amend Article 1 of Chapter 2 of Title 38 of the Official Code of Georgia Annotated, relating to state militia generally, so as to provide for oversight of any deployment of the National Guard by the Governor for state active duty or federal mobilization; to provide for notification, briefing, and reporting requirements; to require approval by the General Assembly prior to certain deployments; to provide for limitations on using the National Guard in certain drug operations and for active combat; to provide for construction; to provide for legislative findings; to provide for definitions; to provide for related matters; to repeal conflicting laws; and for other purposes."}], "other_titles": [], "other_identifiers": [{"identifier": "ocd-bill-ga-2025_26-hb1450"}], "actions": [{"description": "House Hopper", "date": "2026-02-24", "organization_id": "~{\"classification\": \"lower\"}", "classification": ["introduction"], "related_entities": []}, {"description": "House First Readers", "date": "2026-02-25", "organization_id": "~{\"classification\": \"lower\"}", "classification": ["reading-1"], "related_entities": []}, {"description": "House Second Readers", "date": "2026-02-26", "organization_id": "~{\"classification\": \"lower\"}", "classification": ["reading-2"], "related_entities": []}], "sponsorships": [{"name": "Derrick Jackson", "classification": "primary", "entity_type": "person", "primary": true, "person_id": "~{\"name\": \"Derrick Jackson\"}", "organization_id": null}, {"name": "Tremaine Reese", "classification": "primary", "entity_type": "person", "primary": true, "person_id": "~{\"name\": \"Tremaine Reese\"}", "organization_id": null}, {"name": "Billy Mitchell", "classification": "primary", "entity_type": "person", "primary": true, "person_id": "~{\"name\": \"Billy Mitchell\"}", "organization_id": null}, {"name": "Eric Bell", "classification": "primary", "entity_type": "person", "primary": true, "person_id": "~{\"name\": \"Eric Bell\"}", "organization_id": null}, {"name": "Sandra Scott", "classification": "primary", "entity_type": "person", "primary": true, "person_id": "~{\"name\": \"Sandra Scott\"}", "organization_id": null}, {"name": "Viola Davis", "classification": "primary", "entity_type": "person", "primary": true, "person_id": "~{\"name\": \"Viola Davis\"}", "organization_id": null}], "related_bills": [], "versions": [{"note": "LC 63 0100/a", "links": [{"url": "http://www.legis.ga.gov/Legislation/20252026/243902.pdf", "media_type": "application/pdf"}], "date": "", "classification": "", "extras": {"_internal_document_id": 243902, "_version_id": 2}}], "documents": [], "citations": [], "sources": [{"url": "http://webservices.legis.ga.gov/GGAServices/Members/Service.svc?wsdl", "note": "api"}, {"url": "http://webservices.legis.ga.gov/GGAServices/Legislation/Service.svc?wsdl", "note": "api"}, {"url": "https://www.legis.ga.gov/legislation/73613", "note": ""}], "extras": {"guid": 73613}, "jurisdiction": {"id": "ocd-jurisdiction/country:us/state:ga/government", "name": "Georgia", "classification": "state", "division_id": "ocd-division/country:us/state:ga"}, "scraped_at": "2026-04-29T11:27:33+00:00", "_id": "6aaaecb8-43be-11f1-b4ae-1e66d3998f6d"}