{"legislative_session": "2025_26", "identifier": "HR 1393", "title": "House Study Committee on Rural Hospitals; create", "from_organization": "~{\"classification\": \"lower\"}", "classification": ["resolution"], "subject": [], "abstracts": [{"note": "description", "abstract": "A RESOLUTION creating the House Study Committee on Rural Hospitals; and for other purposes."}], "other_titles": [], "other_identifiers": [], "actions": [{"description": "House Hopper", "date": "2026-02-18", "organization_id": "~{\"classification\": \"lower\"}", "classification": ["introduction"], "related_entities": []}], "sponsorships": [{"name": "L.C. Myles", "classification": "primary", "entity_type": "person", "primary": true, "person_id": "~{\"name\": \"L.C. Myles\"}", "organization_id": null}, {"name": "Carolyn Hugley", "classification": "primary", "entity_type": "person", "primary": true, "person_id": "~{\"name\": \"Carolyn Hugley\"}", "organization_id": null}, {"name": "Al Williams", "classification": "primary", "entity_type": "person", "primary": true, "person_id": "~{\"name\": \"Al Williams\"}", "organization_id": null}, {"name": "Debbie Buckner", "classification": "primary", "entity_type": "person", "primary": true, "person_id": "~{\"name\": \"Debbie Buckner\"}", "organization_id": null}, {"name": "Gerald Greene", "classification": "primary", "entity_type": "person", "primary": true, "person_id": "~{\"name\": \"Gerald Greene\"}", "organization_id": null}, {"name": "Robert Dawson", "classification": "primary", "entity_type": "person", "primary": true, "person_id": "~{\"name\": \"Robert Dawson\"}", "organization_id": null}], "related_bills": [], "versions": [{"note": "LC 46 1322/a", "links": [{"url": "http://www.legis.ga.gov/Legislation/20252026/243128.pdf", "media_type": "application/pdf"}], "date": "", "classification": "", "extras": {"_internal_document_id": 243128, "_version_id": 2}}], "documents": [], "citations": [], "sources": [{"url": "http://webservices.legis.ga.gov/GGAServices/Members/Service.svc?wsdl", "note": "api"}, {"url": "http://webservices.legis.ga.gov/GGAServices/Legislation/Service.svc?wsdl", "note": "api"}, {"url": "https://www.legis.ga.gov/legislation/73372", "note": ""}], "extras": {"guid": 73372}, "jurisdiction": {"id": "ocd-jurisdiction/country:us/state:ga/government", "name": "Georgia", "classification": "state", "division_id": "ocd-division/country:us/state:ga"}, "scraped_at": "2026-02-19T10:31:41+00:00", "_id": "2e4c5ab6-0d7e-11f1-8c76-caba7ce1d33e"}