{"legislative_session": "2025_26", "identifier": "HB 1362", "title": "Public officers; persons having certain financial interest shall be ineligible to hold certain public offices; provide", "from_organization": "~{\"classification\": \"lower\"}", "classification": ["bill"], "subject": [], "abstracts": [{"note": "description", "abstract": "A BILL to be entitled an Act to amend Article 1 of Chapter 2 of Title 45 of the Official Code of Georgia Annotated, relating to general provisions for eligibility and qualifications for office, so as to provide that persons having certain financial interest shall be ineligible to hold certain public offices; to amend Part 1 of Article 2 of Chapter 10 of Title 45 of the Official Code of Georgia Annotated, relating to general provisions for conflicts of interest, so as to prohibit state public officials from having financial interest in certain state contracts or from transacting business with the state; to revise disclosure provisions; to revise definitions; to provide for related matters; to repeal conflicting laws; and for other purposes."}], "other_titles": [], "other_identifiers": [], "actions": [{"description": "House Hopper", "date": "2026-02-18", "organization_id": "~{\"classification\": \"lower\"}", "classification": ["introduction"], "related_entities": []}], "sponsorships": [{"name": "Jason Ridley", "classification": "primary", "entity_type": "person", "primary": true, "person_id": "~{\"name\": \"Jason Ridley\"}", "organization_id": null}, {"name": "Trey Rhodes", "classification": "primary", "entity_type": "person", "primary": true, "person_id": "~{\"name\": \"Trey Rhodes\"}", "organization_id": null}, {"name": "James Burchett", "classification": "primary", "entity_type": "person", "primary": true, "person_id": "~{\"name\": \"James Burchett\"}", "organization_id": null}, {"name": "Tyler Paul Smith", "classification": "primary", "entity_type": "person", "primary": true, "person_id": "~{\"name\": \"Tyler Paul Smith\"}", "organization_id": null}, {"name": "John Corbett", "classification": "primary", "entity_type": "person", "primary": true, "person_id": "~{\"name\": \"John Corbett\"}", "organization_id": null}, {"name": "Justin Howard", "classification": "primary", "entity_type": "person", "primary": true, "person_id": "~{\"name\": \"Justin Howard\"}", "organization_id": null}], "related_bills": [], "versions": [{"note": "LC 47 4055/a", "links": [{"url": "http://www.legis.ga.gov/Legislation/20252026/243023.pdf", "media_type": "application/pdf"}], "date": "", "classification": "", "extras": {"_internal_document_id": 243023, "_version_id": 2}}], "documents": [], "citations": [], "sources": [{"url": "http://webservices.legis.ga.gov/GGAServices/Members/Service.svc?wsdl", "note": "api"}, {"url": "http://webservices.legis.ga.gov/GGAServices/Legislation/Service.svc?wsdl", "note": "api"}, {"url": "https://www.legis.ga.gov/legislation/73340", "note": ""}], "extras": {"guid": 73340}, "jurisdiction": {"id": "ocd-jurisdiction/country:us/state:ga/government", "name": "Georgia", "classification": "state", "division_id": "ocd-division/country:us/state:ga"}, "scraped_at": "2026-02-19T09:55:46+00:00", "_id": "29ad7008-0d79-11f1-8c76-caba7ce1d33e"}