{"legislative_session": "2025_26", "identifier": "HR 1893", "title": "House Study Committee on Modernizing the Discovery Process through the Use of New Technologies; create", "from_organization": "~{\"classification\": \"lower\"}", "classification": ["resolution"], "subject": ["GENERAL ASSEMBLY"], "abstracts": [{"note": "description", "abstract": "A RESOLUTION creating the House Study Committee on Modernizing the Discovery Process through the Use of New Technologies; and for other purposes."}], "other_titles": [], "other_identifiers": [{"identifier": "ocd-bill-ga-2025_26-hr1893"}], "actions": [{"description": "House Hopper", "date": "2026-03-25", "organization_id": "~{\"classification\": \"lower\"}", "classification": ["introduction"], "related_entities": []}, {"description": "House First Readers", "date": "2026-03-27", "organization_id": "~{\"classification\": \"lower\"}", "classification": ["reading-1"], "related_entities": []}, {"description": "House Second Readers", "date": "2026-03-31", "organization_id": "~{\"classification\": \"lower\"}", "classification": ["reading-2"], "related_entities": []}], "sponsorships": [{"name": "Bill Fincher", "classification": "primary", "entity_type": "person", "primary": true, "person_id": "~{\"name\": \"Bill Fincher\"}", "organization_id": null}, {"name": "Tyler Paul Smith", "classification": "primary", "entity_type": "person", "primary": true, "person_id": "~{\"name\": \"Tyler Paul Smith\"}", "organization_id": null}, {"name": "Rob Leverett", "classification": "primary", "entity_type": "person", "primary": true, "person_id": "~{\"name\": \"Rob Leverett\"}", "organization_id": null}, {"name": "Clint Crowe", "classification": "primary", "entity_type": "person", "primary": true, "person_id": "~{\"name\": \"Clint Crowe\"}", "organization_id": null}, {"name": "Deborah Silcox", "classification": "primary", "entity_type": "person", "primary": true, "person_id": "~{\"name\": \"Deborah Silcox\"}", "organization_id": null}, {"name": "El-Mahdi Holly", "classification": "primary", "entity_type": "person", "primary": true, "person_id": "~{\"name\": \"El-Mahdi Holly\"}", "organization_id": null}], "related_bills": [], "versions": [{"note": "LC 46 1549/a", "links": [{"url": "http://www.legis.ga.gov/Legislation/20252026/247469.pdf", "media_type": "application/pdf"}], "date": "", "classification": "", "extras": {"_internal_document_id": 247469, "_version_id": 2}}], "documents": [], "citations": [], "sources": [{"url": "http://webservices.legis.ga.gov/GGAServices/Members/Service.svc?wsdl", "note": "api"}, {"url": "http://webservices.legis.ga.gov/GGAServices/Legislation/Service.svc?wsdl", "note": "api"}, {"url": "https://www.legis.ga.gov/legislation/74438", "note": ""}], "extras": {"guid": 74438}, "jurisdiction": {"id": "ocd-jurisdiction/country:us/state:ga/government", "name": "Georgia", "classification": "state", "division_id": "ocd-division/country:us/state:ga"}, "scraped_at": "2026-04-14T11:32:41+00:00", "_id": "a5ae2d9a-37f5-11f1-9d75-fae386648aa6"}