{"legislative_session": "2025_26", "identifier": "HB 1003", "title": "Public officers and employees; daily expense accounts of members of the General Assembly; revise provisions", "from_organization": "~{\"classification\": \"lower\"}", "classification": ["bill"], "subject": [], "abstracts": [{"note": "description", "abstract": "A BILL to be entitled an Act to amend Code Section 45-7-4 of the Official Code of Georgia Annotated, relating to annual salaries of certain state officials and cost-of-living adjustments, so as to revise provisions related to daily expense accounts of members of the General Assembly; to provide members of the General Assembly with an additional security expense allowance; to provide for related matters; to repeal conflicting laws; and for other purposes."}], "other_titles": [], "other_identifiers": [], "actions": [{"description": "House Hopper", "date": "2026-01-16", "organization_id": "~{\"classification\": \"lower\"}", "classification": ["introduction"], "related_entities": []}], "sponsorships": [{"name": "David Wilkerson", "classification": "primary", "entity_type": "person", "primary": true, "person_id": "~{\"name\": \"David Wilkerson\"}", "organization_id": null}, {"name": "Karen Lupton", "classification": "primary", "entity_type": "person", "primary": true, "person_id": "~{\"name\": \"Karen Lupton\"}", "organization_id": null}, {"name": "Esther Panitch", "classification": "primary", "entity_type": "person", "primary": true, "person_id": "~{\"name\": \"Esther Panitch\"}", "organization_id": null}, {"name": "Dar'shun Kendrick", "classification": "primary", "entity_type": "person", "primary": true, "person_id": "~{\"name\": \"Dar'shun Kendrick\"}", "organization_id": null}, {"name": "Lisa Campbell", "classification": "primary", "entity_type": "person", "primary": true, "person_id": "~{\"name\": \"Lisa Campbell\"}", "organization_id": null}, {"name": "Shea Roberts", "classification": "primary", "entity_type": "person", "primary": true, "person_id": "~{\"name\": \"Shea Roberts\"}", "organization_id": null}], "related_bills": [], "versions": [{"note": "LC 47 3779/a", "links": [{"url": "http://www.legis.ga.gov/Legislation/20252026/240037.pdf", "media_type": "application/pdf"}], "date": "", "classification": "", "extras": {"_internal_document_id": 240037, "_version_id": 2}}], "documents": [], "citations": [], "sources": [{"url": "http://webservices.legis.ga.gov/GGAServices/Members/Service.svc?wsdl", "note": "api"}, {"url": "http://webservices.legis.ga.gov/GGAServices/Legislation/Service.svc?wsdl", "note": "api"}, {"url": "https://www.legis.ga.gov/legislation/72298", "note": ""}], "extras": {"guid": 72298}, "jurisdiction": {"id": "ocd-jurisdiction/country:us/state:ga/government", "name": "Georgia", "classification": "state", "division_id": "ocd-division/country:us/state:ga"}, "scraped_at": "2026-01-27T09:32:26+00:00", "_id": "178a727c-fb63-11f0-b65a-82eb2f6ebef7"}