{"legislative_session": "2025_26", "identifier": "SB 569", "title": "Motor Vehicles and Traffic; the issuance of emergency vehicle light permits for towing service companies in certain instances; provide", "from_organization": "~{\"classification\": \"upper\"}", "classification": ["bill"], "subject": [], "abstracts": [{"note": "description", "abstract": "A BILL to be entitled an Act to amend Title 40 of the Official Code of Georgia Annotated, relating to motor vehicles and traffic, so as to provide for the issuance of emergency vehicle light permits for towing service companies in certain instances; to revise a definition; to provide for related matters; to repeal conflicting laws; and for other purposes."}], "other_titles": [], "other_identifiers": [], "actions": [{"description": "Senate Hopper", "date": "2026-02-24", "organization_id": "~{\"classification\": \"upper\"}", "classification": ["introduction"], "related_entities": []}], "sponsorships": [{"name": "Brian Strickland", "classification": "primary", "entity_type": "person", "primary": true, "person_id": "~{\"name\": \"Brian Strickland\"}", "organization_id": null}, {"name": "Randy Robertson", "classification": "primary", "entity_type": "person", "primary": true, "person_id": "~{\"name\": \"Randy Robertson\"}", "organization_id": null}, {"name": "Emanuel Jones", "classification": "primary", "entity_type": "person", "primary": true, "person_id": "~{\"name\": \"Emanuel Jones\"}", "organization_id": null}, {"name": "Carden Summers", "classification": "primary", "entity_type": "person", "primary": true, "person_id": "~{\"name\": \"Carden Summers\"}", "organization_id": null}, {"name": "Derek Mallow", "classification": "primary", "entity_type": "person", "primary": true, "person_id": "~{\"name\": \"Derek Mallow\"}", "organization_id": null}, {"name": "Gail Davenport", "classification": "primary", "entity_type": "person", "primary": true, "person_id": "~{\"name\": \"Gail Davenport\"}", "organization_id": null}], "related_bills": [], "versions": [{"note": "As Introduced LC 39 4969", "links": [{"url": "http://www.legis.ga.gov/Legislation/20252026/243796.pdf", "media_type": "application/pdf"}], "date": "", "classification": "", "extras": {"_internal_document_id": 243796, "_version_id": 2}}], "documents": [], "citations": [], "sources": [{"url": "http://webservices.legis.ga.gov/GGAServices/Members/Service.svc?wsdl", "note": "api"}, {"url": "http://webservices.legis.ga.gov/GGAServices/Legislation/Service.svc?wsdl", "note": "api"}, {"url": "https://www.legis.ga.gov/legislation/73567", "note": ""}], "extras": {"guid": 73567}, "jurisdiction": {"id": "ocd-jurisdiction/country:us/state:ga/government", "name": "Georgia", "classification": "state", "division_id": "ocd-division/country:us/state:ga"}, "scraped_at": "2026-02-25T10:57:16+00:00", "_id": "bfac952a-1238-11f1-a340-6a991ad48986"}