{"legislative_session": "2025_26", "identifier": "SB 603", "title": "\"Georgia Insurance Consumer and Policyholder Advocacy Act\"; enact", "from_organization": "~{\"classification\": \"upper\"}", "classification": ["bill"], "subject": ["INSURANCE"], "abstracts": [{"note": "description", "abstract": "A BILL to be entitled an Act to amend Title 33 of the Official Code of Georgia Annotated, relating to insurance, so as to increase transparency and accountability in the insurance industry and at the office of the Commissioner of Insurance; to provide for related matters; to provide for a short title; to provide for legislative purpose; to provide for an effective date and applicability; to repeal conflicting laws; and for other purposes."}], "other_titles": [], "other_identifiers": [], "actions": [{"description": "Senate Hopper", "date": "2026-02-25", "organization_id": "~{\"classification\": \"upper\"}", "classification": ["introduction"], "related_entities": []}, {"description": "Senate Read and Referred", "date": "2026-02-26", "organization_id": "~{\"classification\": \"upper\"}", "classification": ["referral-committee"], "related_entities": [{"name": "Insurance and Labor", "entity_type": "organization", "organization_id": null}]}], "sponsorships": [{"name": "Nabilah Parkes", "classification": "primary", "entity_type": "person", "primary": true, "person_id": "~{\"name\": \"Nabilah Parkes\"}", "organization_id": null}, {"name": "Randal Mangham", "classification": "primary", "entity_type": "person", "primary": true, "person_id": "~{\"name\": \"Randal Mangham\"}", "organization_id": null}, {"name": "Donzella James", "classification": "primary", "entity_type": "person", "primary": true, "person_id": "~{\"name\": \"Donzella James\"}", "organization_id": null}, {"name": "RaShaun Kemp", "classification": "primary", "entity_type": "person", "primary": true, "person_id": "~{\"name\": \"RaShaun Kemp\"}", "organization_id": null}, {"name": "Sally Harrell", "classification": "primary", "entity_type": "person", "primary": true, "person_id": "~{\"name\": \"Sally Harrell\"}", "organization_id": null}], "related_bills": [], "versions": [{"note": "As Introduced LC 65 0056", "links": [{"url": "http://www.legis.ga.gov/Legislation/20252026/244219.pdf", "media_type": "application/pdf"}], "date": "", "classification": "", "extras": {"_internal_document_id": 244219, "_version_id": 2}}], "documents": [], "citations": [], "sources": [{"url": "http://webservices.legis.ga.gov/GGAServices/Members/Service.svc?wsdl", "note": "api"}, {"url": "http://webservices.legis.ga.gov/GGAServices/Legislation/Service.svc?wsdl", "note": "api"}, {"url": "https://www.legis.ga.gov/legislation/73710", "note": ""}], "extras": {"guid": 73710}, "jurisdiction": {"id": "ocd-jurisdiction/country:us/state:ga/government", "name": "Georgia", "classification": "state", "division_id": "ocd-division/country:us/state:ga"}, "scraped_at": "2026-03-08T10:59:17+00:00", "_id": "da57cd6a-1add-11f1-84a2-7e77e6710f90"}