{"legislative_session": "2025_26", "identifier": "HR 1665", "title": "House Study Committee on Environmental Protection Division Permit and Variance Procedures and Rights to Review; create", "from_organization": "~{\"classification\": \"lower\"}", "classification": ["resolution"], "subject": ["CONSERVATION AND NATURAL RESOURCES", "GENERAL ASSEMBLY"], "abstracts": [{"note": "description", "abstract": "A RESOLUTION creating the House Study Committee on Environmental Protection Division Permit and Variance Procedures and Rights to Review; and for other purposes."}], "other_titles": [], "other_identifiers": [], "actions": [{"description": "House Hopper", "date": "2026-03-12", "organization_id": "~{\"classification\": \"lower\"}", "classification": ["introduction"], "related_entities": []}], "sponsorships": [{"name": "Rick Townsend", "classification": "primary", "entity_type": "person", "primary": true, "person_id": "~{\"name\": \"Rick Townsend\"}", "organization_id": null}, {"name": "Ron Stephens", "classification": "primary", "entity_type": "person", "primary": true, "person_id": "~{\"name\": \"Ron Stephens\"}", "organization_id": null}, {"name": "Lynn Smith", "classification": "primary", "entity_type": "person", "primary": true, "person_id": "~{\"name\": \"Lynn Smith\"}", "organization_id": null}], "related_bills": [], "versions": [{"note": "LC 60 0338/a", "links": [{"url": "http://www.legis.ga.gov/Legislation/20252026/245762.pdf", "media_type": "application/pdf"}], "date": "", "classification": "", "extras": {"_internal_document_id": 245762, "_version_id": 2}}], "documents": [], "citations": [], "sources": [{"url": "http://webservices.legis.ga.gov/GGAServices/Members/Service.svc?wsdl", "note": "api"}, {"url": "http://webservices.legis.ga.gov/GGAServices/Legislation/Service.svc?wsdl", "note": "api"}, {"url": "https://www.legis.ga.gov/legislation/74043", "note": ""}], "extras": {"guid": 74043}, "jurisdiction": {"id": "ocd-jurisdiction/country:us/state:ga/government", "name": "Georgia", "classification": "state", "division_id": "ocd-division/country:us/state:ga"}, "scraped_at": "2026-03-13T10:43:33+00:00", "_id": "7ba73f90-1ec9-11f1-a47a-5a75f050a156"}