{"legislative_session": "2025_26", "identifier": "HB 1274", "title": "Auto Insurance Excess Profits Act; enact", "from_organization": "~{\"classification\": \"lower\"}", "classification": ["bill"], "subject": [], "abstracts": [{"note": "description", "abstract": "A BILL to be entitled an Act to amend Chapter 9 of Title 33 of the Official Code of Georgia Annotated, relating to regulation of rates, underwriting rules, and related organizations, so as to provide for the Department of Insurance to collect certain data annually from insurers writing private passenger automobile insurance policies; to provide for the Commissioner of Insurance to order the refund of any excess profit made by such insurers; to provide for definitions; to provide for calculations; to provide for an order, notice, and opportunity for hearing; to provide for cash refunds or credit refunds; to provide for certification; to provide for rules and regulations; to provide for related matters; to provide for a short title; to provide for an effective date and applicability; to repeal conflicting laws; and for other purposes."}], "other_titles": [], "other_identifiers": [], "actions": [{"description": "House Hopper", "date": "2026-02-11", "organization_id": "~{\"classification\": \"lower\"}", "classification": ["introduction"], "related_entities": []}, {"description": "House First Readers", "date": "2026-02-12", "organization_id": "~{\"classification\": \"lower\"}", "classification": ["reading-1"], "related_entities": []}, {"description": "House Second Readers", "date": "2026-02-17", "organization_id": "~{\"classification\": \"lower\"}", "classification": ["reading-2"], "related_entities": []}], "sponsorships": [{"name": "Matt Reeves", "classification": "primary", "entity_type": "person", "primary": true, "person_id": "~{\"name\": \"Matt Reeves\"}", "organization_id": null}, {"name": "Eddie Lumsden", "classification": "primary", "entity_type": "person", "primary": true, "person_id": "~{\"name\": \"Eddie Lumsden\"}", "organization_id": null}, {"name": "Trey Kelley", "classification": "primary", "entity_type": "person", "primary": true, "person_id": "~{\"name\": \"Trey Kelley\"}", "organization_id": null}, {"name": "Chuck Efstration", "classification": "primary", "entity_type": "person", "primary": true, "person_id": "~{\"name\": \"Chuck Efstration\"}", "organization_id": null}, {"name": "Soo Hong", "classification": "primary", "entity_type": "person", "primary": true, "person_id": "~{\"name\": \"Soo Hong\"}", "organization_id": null}, {"name": "Michelle Au", "classification": "primary", "entity_type": "person", "primary": true, "person_id": "~{\"name\": \"Michelle Au\"}", "organization_id": null}], "related_bills": [], "versions": [{"note": "LC 52 9007/a", "links": [{"url": "http://www.legis.ga.gov/Legislation/20252026/242329.pdf", "media_type": "application/pdf"}], "date": "", "classification": "", "extras": {"_internal_document_id": 242329, "_version_id": 2}}], "documents": [], "citations": [], "sources": [{"url": "http://webservices.legis.ga.gov/GGAServices/Members/Service.svc?wsdl", "note": "api"}, {"url": "http://webservices.legis.ga.gov/GGAServices/Legislation/Service.svc?wsdl", "note": "api"}, {"url": "https://www.legis.ga.gov/legislation/73115", "note": ""}], "extras": {"guid": 73115}, "jurisdiction": {"id": "ocd-jurisdiction/country:us/state:ga/government", "name": "Georgia", "classification": "state", "division_id": "ocd-division/country:us/state:ga"}, "scraped_at": "2026-02-18T09:52:05+00:00", "_id": "7b7604a6-0caf-11f1-aa28-a65f83bf7ccf"}